{
    "display": {
        "icon": {
            "item": "minecraft:lead"
        },
        "title": {
            "text": "Villager Leads",
            "color": "white",
            "bold": false,
            "italic": false
        },
        "description": {
            "text": "Allows leading of villagers",
            "color": "green",
            "bold": false
        },
        "show_toast": false,
        "announce_to_chat": false,
        "frame": "goal"
    },
    "parent": "shroototems_advancement:main/root",
    "criteria": {
        "tick": {
            "trigger": "minecraft:tick"
        }
    }
}